<DocInternals>
  <AlwaysLoose>
    <bool>false</bool>
    <bool>false</bool>
    <bool>false</bool>
    <bool>false</bool>
    <bool>false</bool>
    <bool>false</bool>
    <bool>false</bool>
    <bool>false</bool>
    <bool>false</bool>
    <bool>false</bool>
    <bool>false</bool>
    <bool>false</bool>
    <bool>false</bool>
    <bool>false</bool>
    <bool>false</bool>
    <bool>false</bool>
  </AlwaysLoose>
  <FieldSrcTables>
  </FieldSrcTables>
  <TableViewData>
    <Pos></Pos>
    <CtlInfo>
      <InternalView>
        <Tables>
        </Tables>
        <BroomPoints></BroomPoints>
        <ConnectionPoints>
          <TableViewConnectionPointSaveInfo>
            <Pos>
              <x>899</x>
              <y>500</y>
            </Pos>
            <Fields>
              <String>Member ID</String>
            </Fields>
          </TableViewConnectionPointSaveInfo>
        </ConnectionPoints>
        <ZoomFactor>3FF0000000000000</ZoomFactor>
      </InternalView>
      <SourceView></SourceView>
    </CtlInfo>
    <Mode>0</Mode>
  </TableViewData>
  <Bookmarks></Bookmarks>
  <SavedByVersion>11.20.13206.0409</SavedByVersion>
  <ForceBackEndMacroExecution>false</ForceBackEndMacroExecution>
  <FieldTags>
    <ScriptBased>
      <FieldTagData>
        <Tag>$key</Tag>
        <FieldNames>
          <String>$Field</String>
          <String>$Table</String>
          <String>Member ID</String>
          <String>Quality Measure Abbreviation</String>
        </FieldNames>
      </FieldTagData>
      <FieldTagData>
        <Tag>$hidden</Tag>
        <FieldNames>
          <String>$Field</String>
          <String>$Table</String>
          <String>$Rows</String>
          <String>$Fields</String>
          <String>$FieldNo</String>
          <String>$Info</String>
        </FieldNames>
      </FieldTagData>
      <FieldTagData>
        <Tag>$system</Tag>
        <FieldNames>
          <String>$Field</String>
          <String>$Table</String>
          <String>$Rows</String>
          <String>$Fields</String>
          <String>$FieldNo</String>
          <String>$Info</String>
        </FieldNames>
      </FieldTagData>
      <FieldTagData>
        <Tag>$ascii</Tag>
        <FieldNames>
        </FieldNames>
      </FieldTagData>
      <FieldTagData>
        <Tag>$text</Tag>
        <FieldNames>
        </FieldNames>
      </FieldTagData>
      <FieldTagData>
        <Tag>$numeric</Tag>
        <FieldNames>
        </FieldNames>
      </FieldTagData>
      <FieldTagData>
        <Tag>$integer</Tag>
        <FieldNames>
        </FieldNames>
      </FieldTagData>
      <FieldTagData>
        <Tag>$timestamp</Tag>
        <FieldNames>
        </FieldNames>
      </FieldTagData>
      <FieldTagData>
        <Tag>$date</Tag>
        <FieldNames>
        </FieldNames>
      </FieldTagData>
    </ScriptBased>
    <Interactive></Interactive>
  </FieldTags>
  <FieldComments></FieldComments>
  <TableComments></TableComments>
  <CreatePrjFolder>false</CreatePrjFolder>
  <LinkedTables></LinkedTables>
</DocInternals>
